decline_curve/__init__.py
decline_curve/__main__.py
decline_curve/artifacts.py
decline_curve/backtesting.py
decline_curve/batch.py
decline_curve/benchmark_factory.py
decline_curve/benchmarks.py
decline_curve/calendar.py
decline_curve/catalog.py
decline_curve/cli.py
decline_curve/config.py
decline_curve/data.py
decline_curve/data_contract.py
decline_curve/data_qa.py
decline_curve/dca.py
decline_curve/decline_variants.py
decline_curve/deep_learning.py
decline_curve/defaults.py
decline_curve/diagnostics.py
decline_curve/downtime.py
decline_curve/econ_spec.py
decline_curve/economics.py
decline_curve/ensemble.py
decline_curve/eur_estimation.py
decline_curve/evaluate.py
decline_curve/fit_diagnostics.py
decline_curve/fitting.py
decline_curve/forecast.py
decline_curve/forecast_arima.py
decline_curve/forecast_chronos.py
decline_curve/forecast_deepar.py
decline_curve/forecast_statistical.py
decline_curve/forecast_tft.py
decline_curve/forecast_timesfm.py
decline_curve/history_matching.py
decline_curve/integrations.py
decline_curve/ipr.py
decline_curve/leakage_check.py
decline_curve/logging_config.py
decline_curve/material_balance.py
decline_curve/model_comparison.py
decline_curve/model_interface.py
decline_curve/model_registry.py
decline_curve/models.py
decline_curve/models_arps.py
decline_curve/models_base.py
decline_curve/monte_carlo.py
decline_curve/multiphase.py
decline_curve/multiphase_flow.py
decline_curve/outliers.py
decline_curve/panel_analysis.py
decline_curve/panel_analysis_sweep.py
decline_curve/parameter_resample.py
decline_curve/physics_informed.py
decline_curve/physics_reserves.py
decline_curve/plot.py
decline_curve/portfolio.py
decline_curve/probabilistic_forecast.py
decline_curve/profiling.py
decline_curve/pvt.py
decline_curve/registry.py
decline_curve/reports.py
decline_curve/reserves.py
decline_curve/risk_report.py
decline_curve/rta.py
decline_curve/runner.py
decline_curve/scenarios.py
decline_curve/schemas.py
decline_curve/segmentation.py
decline_curve-0.2.1.dist-info/licenses/LICENSE
decline_curve-0.2.1.dist-info/METADATA
decline_curve-0.2.1.dist-info/WHEEL
decline_curve-0.2.1.dist-info/entry_points.txt
decline_curve-0.2.1.dist-info/top_level.txt
decline_curve-0.2.1.dist-info/RECORD
