Metadata-Version: 2.4
Name: decline-curve
Version: 0.2.1
Summary: Decline Curve Analysis: A comprehensive Python library for decline curve analysis with multi-phase forecasting, data utilities, and ML models
Author-email: "Kyle T. Jones" <kyletjones@gmail.com>
Maintainer-email: "Kyle T. Jones" <kyletjones@gmail.com>
License-Expression: Apache-2.0
Project-URL: Homepage, https://github.com/kylejones200/decline-curve
Project-URL: Documentation, https://decline-curve.readthedocs.io/
Project-URL: Repository, https://github.com/kylejones200/decline-curve
Project-URL: Bug Tracker, https://github.com/kylejones200/decline-curve/issues
Project-URL: Changelog, https://github.com/kylejones200/decline-curve/blob/main/CHANGELOG.md
Keywords: decline-curve-analysis,petroleum-engineering,oil-and-gas,production-forecasting,arps-decline,reserves-estimation,time-series,machine-learning,economic-analysis
Classifier: Development Status :: 4 - Beta
Classifier: Intended Audience :: Science/Research
Classifier: Intended Audience :: Developers
Classifier: Operating System :: OS Independent
Classifier: Programming Language :: Python :: 3
Classifier: Programming Language :: Python :: 3.12
Classifier: Topic :: Scientific/Engineering
Classifier: Topic :: Scientific/Engineering :: Information Analysis
Classifier: Topic :: Software Development :: Libraries :: Python Modules
Classifier: Typing :: Typed
Requires-Python: >=3.12
License-File: LICENSE
Requires-Dist: numpy>=1.23
Requires-Dist: pandas>=2.0
Requires-Dist: scipy>=1.10
Requires-Dist: matplotlib>=3.7
Requires-Dist: tqdm>=4.66
Requires-Dist: numpy-financial>=1.0
Requires-Dist: requests>=2.25
Requires-Dist: xlrd>=2.0
Requires-Dist: numba>=0.58
Requires-Dist: joblib>=1.3
Provides-Extra: stats
Requires-Dist: statsmodels>=0.14; extra == "stats"
Provides-Extra: spatial
Requires-Dist: pykrige>=1.7.0; extra == "spatial"
Requires-Dist: scikit-learn>=1.3; extra == "spatial"
Provides-Extra: integrations
Requires-Dist: pygeomodeling>=0.3.0; extra == "integrations"
Requires-Dist: geosuite>=0.1.0; extra == "integrations"
Requires-Dist: signalplot>=0.1.0; extra == "integrations"
Provides-Extra: llm
Requires-Dist: transformers>=4.41; extra == "llm"
Requires-Dist: torch>=2.0; extra == "llm"
Requires-Dist: accelerate>=0.29; extra == "llm"
Requires-Dist: einops>=0.7; extra == "llm"
Provides-Extra: ml
Requires-Dist: transformers>=4.41; extra == "ml"
Requires-Dist: torch>=2.0; extra == "ml"
Requires-Dist: accelerate>=0.29; extra == "ml"
Requires-Dist: einops>=0.7; extra == "ml"
Requires-Dist: scikit-learn>=1.3; extra == "ml"
Provides-Extra: benchmark
Requires-Dist: mlflow>=2.0; extra == "benchmark"
Requires-Dist: pyyaml>=6.0; extra == "benchmark"
Provides-Extra: config
Requires-Dist: tomli>=2.0.0; python_version < "3.11" and extra == "config"
Requires-Dist: pyyaml>=6.0; extra == "config"
Provides-Extra: reports
Requires-Dist: reportlab>=4.0.0; extra == "reports"
Provides-Extra: dev
Requires-Dist: pytest>=7.0; extra == "dev"
Requires-Dist: pytest-cov>=4.0; extra == "dev"
Requires-Dist: pytest-xdist>=3.0; extra == "dev"
Requires-Dist: black>=23.0; extra == "dev"
Requires-Dist: isort>=5.12; extra == "dev"
Requires-Dist: flake8>=6.0; extra == "dev"
Requires-Dist: mypy>=1.0; extra == "dev"
Requires-Dist: types-requests>=2.32; extra == "dev"
Requires-Dist: pre-commit>=3.0; extra == "dev"
Requires-Dist: line_profiler>=4.0; extra == "dev"
Provides-Extra: docs
Requires-Dist: sphinx>=7.0; extra == "docs"
Requires-Dist: sphinx-rtd-theme>=2.0; extra == "docs"
Requires-Dist: sphinx-autodoc-typehints>=1.20; extra == "docs"
Provides-Extra: examples
Requires-Dist: jupyter>=1.0; extra == "examples"
Requires-Dist: notebook>=7.0; extra == "examples"
Requires-Dist: ipykernel>=6.0; extra == "examples"
Provides-Extra: all
Requires-Dist: decline-curve[dev,docs,examples,integrations,llm,ml,spatial,stats]; extra == "all"
Dynamic: license-file
